<?xml version="1.0" encoding="utf-8"?>
<document>
  <QAS>
    <Chapter>V</Chapter>
    <Article>56</Article>
    <Clause>1</Clause>
    <Questions>
      <Question>Người tiêu dùng có quyền gì khi muốn giải quyết tranh chấp với doanh nghiệp?</Question>
    </Questions>
    <Answers>
      <Answer>Theo Chương V, Mục 2, Điều 56, khoản 1: Người tiêu dùng có quyền yêu cầu tổ chức, cá nhân kinh doanh thương lượng để giải quyết tranh chấp phát sinh.</Answer>
    </Answers>
  </QAS>
  <QAS>
    <Chapter>V</Chapter>
    <Article>56</Article>
    <Clause>2</Clause>
    <Questions>
      <Question>Doanh nghiệp có nghĩa vụ gì khi nhận được yêu cầu thương lượng từ khách hàng?</Question>
    </Questions>
    <Answers>
      <Answer>Theo Chương V, Mục 2, Điều 56, khoản 2: Tổ chức, cá nhân kinh doanh phải tiếp nhận yêu cầu thương lượng của người tiêu dùng theo quy định tại Điều 57 của Luật này.</Answer>
    </Answers>
  </QAS>
  <QAS>
    <Chapter>V</Chapter>
    <Article>56</Article>
    <Clause>3</Clause>
    <Questions>
      <Question>Nếu công ty từ chối thương lượng không có lý do, người tiêu dùng có thể làm gì?</Question>
    </Questions>
    <Answers>
      <Answer>Theo Chương V, Mục 2, Điều 56, khoản 3: Trường hợp tổ chức, cá nhân kinh doanh không trả lời yêu cầu thương lượng hoặc từ chối thương lượng mà không có lý do chính đáng, người tiêu dùng có quyền yêu cầu cơ quan quản lý nhà nước về bảo vệ quyền lợi người tiêu dùng, tổ chức xã hội tham gia bảo vệ quyền lợi người tiêu dùng hỗ trợ thương lượng.</Answer>
    </Answers>
  </QAS>
  <QAS>
    <Chapter>V</Chapter>
    <Article>56</Article>
    <Clause>3</Clause>
    <Questions>
      <Question>Khách hàng có thể yêu cầu ai hỗ trợ thương lượng khi doanh nghiệp không hợp tác?</Question>
    </Questions>
    <Answers>
      <Answer>Theo Chương V, Mục 2, Điều 56, khoản 3: Người tiêu dùng có quyền yêu cầu cơ quan quản lý nhà nước về bảo vệ quyền lợi người tiêu dùng hoặc tổ chức xã hội tham gia bảo vệ quyền lợi người tiêu dùng hỗ trợ thương lượng khi quyền, lợi ích hợp pháp của mình bị xâm phạm.</Answer>
    </Answers>
  </QAS>
  <QAS>
    <Chapter>V</Chapter>
    <Article>56</Article>
    <Clause>1</Clause>
    <Questions>
      <Question>Quyền thương lượng của người tiêu dùng được quy định như thế nào?</Question>
    </Questions>
    <Answers>
      <Answer>Theo Chương V về Giải quyết tranh chấp giữa người tiêu dùng và tổ chức, cá nhân kinh doanh, Mục 2 về Thương lượng, Điều 56, khoản 1: Người tiêu dùng có quyền yêu cầu tổ chức, cá nhân kinh doanh thương lượng một cách chủ động.</Answer>
    </Answers>
  </QAS>
  <QAS>
    <Chapter>V</Chapter>
    <Article>56</Article>
    <Clause>2</Clause>
    <Questions>
      <Question>Doanh nghiệp có được từ chối thương lượng với khách hàng không?</Question>
    </Questions>
    <Answers>
      <Answer>Theo Chương V, Mục 2, Điều 56, khoản 2 và khoản 3: Tổ chức, cá nhân kinh doanh phải tiếp nhận yêu cầu thương lượng của người tiêu dùng. Nếu từ chối thương lượng mà không có lý do chính đáng, người tiêu dùng có quyền yêu cầu cơ quan có thẩm quyền hỗ trợ.</Answer>
    </Answers>
  </QAS>
  <QAS>
    <Chapter>V</Chapter>
    <Article>56</Article>
    <Clause>3</Clause>
    <Questions>
      <Question>Khi nào người tiêu dùng được yêu cầu hỗ trợ thương lượng từ cơ quan nhà nước?</Question>
    </Questions>
    <Answers>
      <Answer>Theo Chương V, Mục 2, Điều 56, khoản 3: Khi tổ chức, cá nhân kinh doanh không trả lời yêu cầu thương lượng theo quy định tại Điều 57 hoặc từ chối thương lượng mà không có lý do chính đáng, và khi quyền, lợi ích hợp pháp của người tiêu dùng bị xâm phạm.</Answer>
    </Answers>
  </QAS>
  <QAS>
    <Chapter>V</Chapter>
    <Article>56</Article>
    <Clause>2</Clause>
    <Questions>
      <Question>Quy trình thương lượng giữa người tiêu dùng và doanh nghiệp được quy định ở đâu?</Question>
    </Questions>
    <Answers>
      <Answer>Theo Chương V, Mục 2, Điều 56, khoản 2: Tổ chức, cá nhân kinh doanh phải tiếp nhận yêu cầu thương lượng của người tiêu dùng theo quy định tại Điều 57 của Luật này, trong đó Điều 57 quy định chi tiết về trình tự, thủ tục thương lượng.</Answer>
    </Answers>
  </QAS>
  <QAS>
    <Chapter>V</Chapter>
    <Article>56</Article>
    <Clause>3</Clause>
    <Questions>
      <Question>Ai có thể hỗ trợ người tiêu dùng trong quá trình thương lượng?</Question>
    </Questions>
    <Answers>
      <Answer>Theo Chương V, Mục 2, Điều 56, khoản 3: Có hai đối tượng có thể hỗ trợ là cơ quan quản lý nhà nước về bảo vệ quyền lợi người tiêu dùng và tổ chức xã hội tham gia bảo vệ quyền lợi người tiêu dùng.</Answer>
    </Answers>
  </QAS>
  <QAS>
    <Chapter>V</Chapter>
    <Article>56</Article>
    <Clause>1</Clause>
    <Questions>
      <Question>Người mua hàng có quyền gì khi muốn giải quyết vấn đề với người bán?</Question>
    </Questions>
    <Answers>
      <Answer>Theo Chương V về Giải quyết tranh chấp giữa người tiêu dùng và tổ chức, cá nhân kinh doanh, Mục 2 về Thương lượng, Điều 56, khoản 1: Người tiêu dùng có quyền yêu cầu tổ chức, cá nhân kinh doanh thương lượng để giải quyết các vấn đề phát sinh.</Answer>
    </Answers>
  </QAS>
  <QAS>
    <Chapter>V</Chapter>
    <Article>56</Article>
    <Clause>2</Clause>
    <Questions>
      <Question>Nghĩa vụ của công ty khi khách hàng yêu cầu thương lượng là gì?</Question>
    </Questions>
    <Answers>
      <Answer>Theo Chương V, Mục 2, Điều 56, khoản 2: Nghĩa vụ của tổ chức, cá nhân kinh doanh là phải tiếp nhận yêu cầu thương lượng của người tiêu dùng theo đúng quy định tại Điều 57 của Luật này.</Answer>
    </Answers>
  </QAS>
  <QAS>
    <Chapter>V</Chapter>
    <Article>56</Article>
    <Clause>3</Clause>
    <Questions>
      <Question>Nếu doanh nghiệp không phản hồi yêu cầu thương lượng thì sao?</Question>
    </Questions>
    <Answers>
      <Answer>Theo Chương V, Mục 2, Điều 56, khoản 3: Trường hợp tổ chức, cá nhân kinh doanh không trả lời yêu cầu thương lượng của người tiêu dùng theo quy định tại Điều 57, người tiêu dùng có quyền yêu cầu cơ quan quản lý nhà nước về bảo vệ quyền lợi người tiêu dùng hỗ trợ thương lượng.</Answer>
    </Answers>
  </QAS>
  <QAS>
    <Chapter>V</Chapter>
    <Article>56</Article>
    <Clause>3</Clause>
    <Questions>
      <Question>Điều kiện để người tiêu dùng được hỗ trợ thương lượng là gì?</Question>
    </Questions>
    <Answers>
      <Answer>Theo Chương V, Mục 2, Điều 56, khoản 3: Điều kiện là khi quyền, lợi ích hợp pháp của người tiêu dùng bị xâm phạm và tổ chức, cá nhân kinh doanh không trả lời yêu cầu thương lượng hoặc từ chối thương lượng mà không có lý do chính đáng.</Answer>
    </Answers>
  </QAS>
  <QAS>
    <Chapter>V</Chapter>
    <Article>56</Article>
    <Clause>1</Clause>
    <Questions>
      <Question>Quyền yêu cầu thương lượng của khách hàng có bị hạn chế không?</Question>
    </Questions>
    <Answers>
      <Answer>Theo Chương V, Mục 2, Điều 56, khoản 1: Quyền yêu cầu thương lượng của người tiêu dùng không bị hạn chế, đây là quyền cơ bản được pháp luật bảo đảm trong mối quan hệ với tổ chức, cá nhân kinh doanh.</Answer>
    </Answers>
  </QAS>
  <QAS>
    <Chapter>V</Chapter>
    <Article>56</Article>
    <Clause>3</Clause>
    <Questions>
      <Question>Tổ chức xã hội có vai trò gì trong việc hỗ trợ thương lượng?</Question>
    </Questions>
    <Answers>
      <Answer>Theo Chương V, Mục 2, Điều 56, khoản 3: Tổ chức xã hội tham gia bảo vệ quyền lợi người tiêu dùng có vai trò hỗ trợ thương lượng khi người tiêu dùng yêu cầu, đặc biệt khi quyền, lợi ích hợp pháp của họ bị xâm phạm.</Answer>
    </Answers>
  </QAS>
  <QAS>
    <Chapter>V</Chapter>
    <Article>56</Article>
    <Clause>1</Clause>
    <Questions>
      <Question>Làm thế nào để khách hàng có thể yêu cầu thương lượng với doanh nghiệp?</Question>
    </Questions>
    <Answers>
      <Answer>Theo Chương V, Mục 2, Điều 56: Người tiêu dùng có quyền yêu cầu tổ chức, cá nhân kinh doanh thương lượng theo khoản 1, và việc tiếp nhận sẽ được thực hiện theo quy định tại Điều 57 về trình tự, thủ tục thương lượng.</Answer>
    </Answers>
  </QAS>
  <QAS>
    <Chapter>V</Chapter>
    <Article>56</Article>
    <Clause>3</Clause>
    <Questions>
      <Question>Khi doanh nghiệp từ chối thương lượng có lý do chính đáng thì sao?</Question>
    </Questions>
    <Answers>
      <Answer>Theo Chương V, Mục 2, Điều 56, khoản 3: Chỉ khi tổ chức, cá nhân kinh doanh từ chối thương lượng mà không có lý do chính đáng thì người tiêu dùng mới có quyền yêu cầu cơ quan có thẩm quyền hỗ trợ. Nếu có lý do chính đáng thì việc từ chối là hợp lý.</Answer>
    </Answers>
  </QAS>
  <QAS>
    <Chapter>V</Chapter>
    <Article>56</Article>
    <Clause>3</Clause>
    <Questions>
      <Question>Cơ quan nào có thẩm quyền hỗ trợ thương lượng cho người tiêu dùng?</Question>
    </Questions>
    <Answers>
      <Answer>Theo Chương V, Mục 2, Điều 56, khoản 3: Cơ quan quản lý nhà nước về bảo vệ quyền lợi người tiêu dùng có thẩm quyền hỗ trợ thương lượng khi người tiêu dùng có yêu cầu trong trường hợp quy định.</Answer>
    </Answers>
  </QAS>
  <QAS>
    <Chapter>V</Chapter>
    <Article>56</Article>
    <Clause/>
    <Questions>
      <Question>Thương lượng là phương thức giải quyết tranh chấp như thế nào?</Question>
    </Questions>
    <Answers>
      <Answer>Theo Chương V về Giải quyết tranh chấp giữa người tiêu dùng và tổ chức, cá nhân kinh doanh, Mục 2 về Thương lượng, Điều 56: Thương lượng là phương thức giải quyết tranh chấp dựa trên quyền yêu cầu của người tiêu dùng và nghĩa vụ tiếp nhận của tổ chức, cá nhân kinh doanh.</Answer>
    </Answers>
  </QAS>
  <QAS>
    <Chapter>V</Chapter>
    <Article>56</Article>
    <Clause>1</Clause>
    <Questions>
      <Question>Người tiêu dùng bị xâm phạm quyền lợi có thể làm gì?</Question>
    </Questions>
    <Answers>
      <Answer>Theo Chương V, Mục 2, Điều 56, khoản 1 và khoản 3: Người tiêu dùng có quyền yêu cầu tổ chức, cá nhân kinh doanh thương lượng, và nếu bị từ chối mà không có lý do chính đáng thì có thể yêu cầu cơ quan quản lý nhà nước hoặc tổ chức xã hội hỗ trợ thương lượng.</Answer>
    </Answers>
  </QAS>
  <QAS>
    <Chapter>V</Chapter>
    <Article>56</Article>
    <Clause/>
    <Questions>
      <Question>Quy định về yêu cầu và tiếp nhận thương lượng ở điều nào?</Question>
    </Questions>
    <Answers>
      <Answer>Theo Chương V về Giải quyết tranh chấp giữa người tiêu dùng và tổ chức, cá nhân kinh doanh, Mục 2 về Thương lượng, Điều 56 quy định về yêu cầu và tiếp nhận thương lượng với 3 khoản cụ thể.</Answer>
    </Answers>
  </QAS>
  <QAS>
    <Chapter>V</Chapter>
    <Article>56</Article>
    <Clause>3</Clause>
    <Questions>
      <Question>Doanh nghiệp có thể từ chối thương lượng trong trường hợp nào?</Question>
    </Questions>
    <Answers>
      <Answer>Theo Chương V, Mục 2, Điều 56, khoản 3: Tổ chức, cá nhân kinh doanh chỉ có thể từ chối thương lượng khi có lý do chính đáng. Nếu từ chối mà không có lý do chính đáng thì người tiêu dùng có quyền yêu cầu cơ quan có thẩm quyền hỗ trợ.</Answer>
    </Answers>
  </QAS>
  <QAS>
    <Chapter>V</Chapter>
    <Article>56</Article>
    <Clause>2</Clause>
    <Questions>
      <Question>Ai chịu trách nhiệm tiếp nhận yêu cầu thương lượng từ khách hàng?</Question>
    </Questions>
    <Answers>
      <Answer>Theo Chương V, Mục 2, Điều 56, khoản 2: Tổ chức, cá nhân kinh doanh chịu trách nhiệm phải tiếp nhận yêu cầu thương lượng của người tiêu dùng theo quy định tại Điều 57 của Luật này.</Answer>
    </Answers>
  </QAS>
  <QAS>
    <Chapter>V</Chapter>
    <Article>56</Article>
    <Clause>3</Clause>
    <Questions>
      <Question>Khi nào người tiêu dùng cần hỗ trợ thương lượng từ bên thứ ba?</Question>
    </Questions>
    <Answers>
      <Answer>Theo Chương V, Mục 2, Điều 56, khoản 3: Khi tổ chức, cá nhân kinh doanh không trả lời yêu cầu thương lượng theo quy định tại Điều 57 hoặc từ chối thương lượng mà không có lý do chính đáng, và khi quyền, lợi ích hợp pháp của người tiêu dùng bị xâm phạm.</Answer>
    </Answers>
  </QAS>
  <QAS>
    <Chapter>V</Chapter>
    <Article>56</Article>
    <Clause>2</Clause>
    <Questions>
      <Question>Quyền thương lượng của người tiêu dùng được bảo vệ như thế nào?</Question>
    </Questions>
    <Answers>
      <Answer>Theo Chương V, Mục 2, Điều 56: Quyền thương lượng được bảo vệ thông qua nghĩa vụ tiếp nhận của doanh nghiệp (khoản 2) và cơ chế hỗ trợ từ cơ quan nhà nước và tổ chức xã hội khi doanh nghiệp không hợp tác (khoản 3).</Answer>
    </Answers>
  </QAS>
  <QAS>
    <Chapter>V</Chapter>
    <Article>56</Article>
    <Clause>1</Clause>
    <Questions>
      <Question>Điều 56 quy định gì về quyền của người tiêu dùng?</Question>
    </Questions>
    <Answers>
      <Answer>Theo Chương V, Mục 2, Điều 56, khoản 1: Quy định quyền cơ bản của người tiêu dùng là có quyền yêu cầu tổ chức, cá nhân kinh doanh thương lượng để giải quyết các vấn đề phát sinh trong quá trình giao dịch.</Answer>
    </Answers>
  </QAS>
  <QAS>
    <Chapter>V</Chapter>
    <Article>56</Article>
    <Clause>2</Clause>
    <Questions>
      <Question>Nghĩa vụ pháp lý của doanh nghiệp đối với yêu cầu thương lượng?</Question>
    </Questions>
    <Answers>
      <Answer>Theo Chương V, Mục 2, Điều 56, khoản 2: Nghĩa vụ pháp lý của tổ chức, cá nhân kinh doanh là phải tiếp nhận yêu cầu thương lượng của người tiêu dùng theo đúng quy định tại Điều 57 của Luật này.</Answer>
    </Answers>
  </QAS>
  <QAS>
    <Chapter>V</Chapter>
    <Article>56</Article>
    <Clause>3</Clause>
    <Questions>
      <Question>Hậu quả khi doanh nghiệp không tuân thủ quy định thương lượng?</Question>
    </Questions>
    <Answers>
      <Answer>Theo Chương V, Mục 2, Điều 56, khoản 3: Hậu quả là người tiêu dùng có quyền yêu cầu cơ quan quản lý nhà nước về bảo vệ quyền lợi người tiêu dùng hoặc tổ chức xã hội tham gia bảo vệ quyền lợi người tiêu dùng hỗ trợ thương lượng.</Answer>
    </Answers>
  </QAS>
  <QAS>
    <Chapter>V</Chapter>
    <Article>56</Article>
    <Clause>3</Clause>
    <Questions>
      <Question>Cách thức yêu cầu hỗ trợ thương lượng từ cơ quan nhà nước?</Question>
    </Questions>
    <Answers>
      <Answer>Theo Chương V, Mục 2, Điều 56, khoản 3: Người tiêu dùng có quyền yêu cầu cơ quan quản lý nhà nước về bảo vệ quyền lợi người tiêu dùng hỗ trợ thương lượng khi quyền, lợi ích hợp pháp của mình bị xâm phạm và doanh nghiệp không hợp tác.</Answer>
    </Answers>
  </QAS>
  <QAS>
    <Chapter>V</Chapter>
    <Article>56</Article>
    <Clause/>
    <Questions>
      <Question>Vai trò của luật trong việc bảo vệ quyền thương lượng?</Question>
    </Questions>
    <Answers>
      <Answer>Theo Chương V về Giải quyết tranh chấp giữa người tiêu dùng và tổ chức, cá nhân kinh doanh, Mục 2 về Thương lượng, Điều 56: Luật tạo ra khuôn khổ pháp lý bảo vệ quyền thương lượng thông qua việc quy định quyền của người tiêu dùng và nghĩa vụ của doanh nghiệp.</Answer>
    </Answers>
  </QAS>
  <QAS>
    <Chapter>V</Chapter>
    <Article>56</Article>
    <Clause>2</Clause>
    <Questions>
      <Question>Thủ tục thương lượng được quy định chi tiết ở đâu?</Question>
    </Questions>
    <Answers>
      <Answer>Theo Chương V, Mục 2, Điều 56, khoản 2: Thủ tục thương lượng được quy định chi tiết tại Điều 57 của Luật này, mà tổ chức, cá nhân kinh doanh phải tuân thủ khi tiếp nhận yêu cầu thương lượng.</Answer>
    </Answers>
  </QAS>
  <QAS>
    <Chapter>V</Chapter>
    <Article>56</Article>
    <Clause>3</Clause>
    <Questions>
      <Question>Điều kiện để được hỗ trợ thương lượng từ tổ chức xã hội?</Question>
    </Questions>
    <Answers>
      <Answer>Theo Chương V, Mục 2, Điều 56, khoản 3: Điều kiện là quyền, lợi ích hợp pháp của người tiêu dùng bị xâm phạm và tổ chức, cá nhân kinh doanh không trả lời yêu cầu thương lượng hoặc từ chối thương lượng mà không có lý do chính đáng.</Answer>
    </Answers>
  </QAS>
  <QAS>
    <Chapter>V</Chapter>
    <Article>56</Article>
    <Clause>1</Clause>
    <Questions>
      <Question>Quyền lợi người tiêu dùng được bảo vệ như thế nào trong thương lượng?</Question>
    </Questions>
    <Answers>
      <Answer>Theo Chương V, Mục 2, Điều 56: Quyền lợi người tiêu dùng được bảo vệ thông qua quyền yêu cầu thương lượng (khoản 1), nghĩa vụ tiếp nhận của doanh nghiệp (khoản 2), và cơ chế hỗ trợ từ cơ quan có thẩm quyền khi cần thiết (khoản 3).</Answer>
    </Answers>
  </QAS>
  <QAS>
    <Chapter>V</Chapter>
    <Article>56</Article>
    <Clause/>
    <Questions>
      <Question>Ý nghĩa của việc quy định quyền thương lượng trong luật?</Question>
    </Questions>
    <Answers>
      <Answer>Theo Chương V về Giải quyết tranh chấp giữa người tiêu dùng và tổ chức, cá nhân kinh doanh, Mục 2 về Thương lượng, Điều 56: Việc quy định quyền thương lượng tạo cơ sở pháp lý để người tiêu dùng chủ động giải quyết tranh chấp một cách hòa bình và hiệu quả.</Answer>
    </Answers>
  </QAS>
  <QAS>
    <Chapter>V</Chapter>
    <Article>56</Article>
    <Clause>3</Clause>
    <Questions>
      <Question>Cơ chế bảo vệ người tiêu dùng khi thương lượng thất bại?</Question>
    </Questions>
    <Answers>
      <Answer>Theo Chương V, Mục 2, Điều 56, khoản 3: Cơ chế bảo vệ là người tiêu dùng có quyền yêu cầu cơ quan quản lý nhà nước về bảo vệ quyền lợi người tiêu dùng hoặc tổ chức xã hội tham gia bảo vệ quyền lợi người tiêu dùng hỗ trợ thương lượng.</Answer>
    </Answers>
  </QAS>
  <QAS>
    <Chapter>V</Chapter>
    <Article>56</Article>
    <Clause>3</Clause>
    <Questions>
      <Question>Doanh nghiệp vi phạm quy định thương lượng sẽ bị xử lý sao?</Question>
    </Questions>
    <Answers>
      <Answer>Theo Chương V, Mục 2, Điều 56, khoản 3: Khi tổ chức, cá nhân kinh doanh không trả lời yêu cầu thương lượng hoặc từ chối thương lượng mà không có lý do chính đáng, người tiêu dùng có quyền yêu cầu cơ quan có thẩm quyền can thiệp hỗ trợ.</Answer>
    </Answers>
  </QAS>
  <QAS>
    <Chapter>V</Chapter>
    <Article>56</Article>
    <Clause/>
    <Questions>
      <Question>Phạm vi áp dụng của quy định thương lượng?</Question>
    </Questions>
    <Answers>
      <Answer>Theo Chương V về Giải quyết tranh chấp giữa người tiêu dùng và tổ chức, cá nhân kinh doanh, Mục 2 về Thương lượng, Điều 56: Quy định áp dụng cho mọi tranh chấp phát sinh giữa người tiêu dùng và tổ chức, cá nhân kinh doanh trong các giao dịch thương mại.</Answer>
    </Answers>
  </QAS>
  <QAS>
    <Chapter>V</Chapter>
    <Article>56</Article>
    <Clause>1</Clause>
    <Questions>
      <Question>Quyền và nghĩa vụ trong quan hệ thương lượng được quy định thế nào?</Question>
    </Questions>
    <Answers>
      <Answer>Theo Chương V, Mục 2, Điều 56: Quyền của người tiêu dùng là yêu cầu thương lượng (khoản 1), nghĩa vụ của tổ chức, cá nhân kinh doanh là phải tiếp nhận (khoản 2), và có cơ chế hỗ trợ khi cần thiết (khoản 3).</Answer>
    </Answers>
  </QAS>
  <QAS>
    <Chapter>V</Chapter>
    <Article>56</Article>
    <Clause>2</Clause>
    <Questions>
      <Question>Tính bắt buộc của việc tiếp nhận yêu cầu thương lượng?</Question>
    </Questions>
    <Answers>
      <Answer>Theo Chương V, Mục 2, Điều 56, khoản 2: Việc tiếp nhận yêu cầu thương lượng của người tiêu dùng là bắt buộc đối với tổ chức, cá nhân kinh doanh và phải tuân thủ theo quy định tại Điều 57 của Luật này.</Answer>
    </Answers>
  </QAS>
  <QAS>
    <Chapter>V</Chapter>
    <Article>56</Article>
    <Clause>3</Clause>
    <Questions>
      <Question>Cơ sở pháp lý để yêu cầu hỗ trợ thương lượng?</Question>
    </Questions>
    <Answers>
      <Answer>Theo Chương V, Mục 2, Điều 56, khoản 3: Cơ sở pháp lý là khi tổ chức, cá nhân kinh doanh không trả lời yêu cầu thương lượng theo quy định tại Điều 57 hoặc từ chối thương lượng mà không có lý do chính đáng, và quyền, lợi ích hợp pháp của người tiêu dùng bị xâm phạm.</Answer>
    </Answers>
  </QAS>
  <QAS>
    <Chapter>V</Chapter>
    <Article>56</Article>
    <Clause>1</Clause>
    <Questions>
      <Question>Đối tượng có thể yêu cầu thương lượng là ai?</Question>
    </Questions>
    <Answers>
      <Answer>Theo Chương V, Mục 2, Điều 56, khoản 1: Đối tượng có thể yêu cầu thương lượng là người tiêu dùng trong mối quan hệ với tổ chức, cá nhân kinh doanh khi có tranh chấp phát sinh.</Answer>
    </Answers>
  </QAS>
  <QAS>
    <Chapter>V</Chapter>
    <Article>56</Article>
    <Clause>2</Clause>
    <Questions>
      <Question>Đối tượng có nghĩa vụ tiếp nhận yêu cầu thương lượng?</Question>
    </Questions>
    <Answers>
      <Answer>Theo Chương V, Mục 2, Điều 56, khoản 2: Đối tượng có nghĩa vụ tiếp nhận yêu cầu thương lượng là tổ chức, cá nhân kinh doanh và phải thực hiện theo quy định tại Điều 57 của Luật này.</Answer>
    </Answers>
  </QAS>
  <QAS>
    <Chapter>V</Chapter>
    <Article>56</Article>
    <Clause>3</Clause>
    <Questions>
      <Question>Hình thức hỗ trợ thương lượng từ cơ quan nhà nước?</Question>
    </Questions>
    <Answers>
      <Answer>Theo Chương V, Mục 2, Điều 56, khoản 3: Hình thức hỗ trợ là cơ quan quản lý nhà nước về bảo vệ quyền lợi người tiêu dùng và tổ chức xã hội tham gia bảo vệ quyền lợi người tiêu dùng sẽ hỗ trợ thương lượng khi người tiêu dùng yêu cầu.</Answer>
    </Answers>
  </QAS>
  <QAS>
    <Chapter>V</Chapter>
    <Article>56</Article>
    <Clause/>
    <Questions>
      <Question>Điều 56 thuộc chương và mục nào của luật?</Question>
    </Questions>
    <Answers>
      <Answer>Theo cấu trúc luật, Điều 56 về yêu cầu và tiếp nhận thương lượng thuộc Chương V về Giải quyết tranh chấp giữa người tiêu dùng và tổ chức, cá nhân kinh doanh, cụ thể là Mục 2 về Thương lượng.</Answer>
    </Answers>
  </QAS>
  <QAS>
    <Chapter>V</Chapter>
    <Article>56</Article>
    <Clause>1</Clause>
    <Questions>
      <Question>Tầm quan trọng của quy định thương lượng trong bảo vệ người tiêu dùng?</Question>
    </Questions>
    <Answers>
      <Answer>Theo Chương V, Mục 2, Điều 56: Quy định thương lượng có tầm quan trọng lớn vì tạo ra phương thức giải quyết tranh chấp đầu tiên, cho phép người tiêu dùng chủ động bảo vệ quyền lợi thông qua quyền yêu cầu (khoản 1) và nghĩa vụ tiếp nhận của doanh nghiệp (khoản 2).</Answer>
    </Answers>
  </QAS>
  <QAS>
    <Chapter>V</Chapter>
    <Article>56</Article>
    <Clause>2</Clause>
    <Questions>
      <Question>Mối liên hệ giữa Điều 56 và Điều 57?</Question>
    </Questions>
    <Answers>
      <Answer>Theo Chương V, Mục 2, Điều 56, khoản 2: Điều 56 quy định nguyên tắc chung về quyền yêu cầu và nghĩa vụ tiếp nhận thương lượng, trong khi việc tiếp nhận phải tuân thủ theo quy định chi tiết tại Điều 57 về trình tự, thủ tục thương lượng.</Answer>
    </Answers>
  </QAS>
  <QAS>
    <Chapter>V</Chapter>
    <Article>56</Article>
    <Clause>2</Clause>
    <Questions>
      <Question>Bảo đảm thực hiện quyền thương lượng của người tiêu dùng?</Question>
    </Questions>
    <Answers>
      <Answer>Theo Chương V, Mục 2, Điều 56: Quyền thương lượng được bảo đảm thực hiện thông qua nghĩa vụ pháp lý của doanh nghiệp phải tiếp nhận (khoản 2) và cơ chế hỗ trợ từ cơ quan nhà nước và tổ chức xã hội khi doanh nghiệp không tuân thủ (khoản 3).</Answer>
    </Answers>
  </QAS>
</document>
